.gitignore
LICENSE
README.md
boston.csv
example_boston.py
example_simulated.py
setup.cfg
setup.py
test_rulefit.py
.github/workflows/python-package.yml
.github/workflows/python-publish.yml
RuleFit.egg-info/PKG-INFO
RuleFit.egg-info/SOURCES.txt
RuleFit.egg-info/dependency_links.txt
RuleFit.egg-info/requires.txt
RuleFit.egg-info/top_level.txt
rulefit/__init__.py
rulefit/rulefit.py
rulefit.egg-info/PKG-INFO
rulefit.egg-info/SOURCES.txt
rulefit.egg-info/dependency_links.txt
rulefit.egg-info/requires.txt
rulefit.egg-info/top_level.txt