Metadata-Version: 1.0
Name: rulefit
Version: 0.3.1
Summary: RuleFit algorithm
Home-page: https://github.com/rohan-gt/rulefit
Author: Rohan George Thampi
Author-email: rohangt1591@gmail.com
License: UNKNOWN
Platform: UNKNOWN
